odoo/addons/mgmtsystem_audit/README.rst
odoo/addons/mgmtsystem_audit/__init__.py
odoo/addons/mgmtsystem_audit/__manifest__.py
odoo/addons/mgmtsystem_audit/data/audit_automated_actions.xml
odoo/addons/mgmtsystem_audit/data/audit_sequence.xml
odoo/addons/mgmtsystem_audit/demo/demo_audit.xml
odoo/addons/mgmtsystem_audit/i18n/am.po
odoo/addons/mgmtsystem_audit/i18n/ca.po
odoo/addons/mgmtsystem_audit/i18n/de.po
odoo/addons/mgmtsystem_audit/i18n/el_GR.po
odoo/addons/mgmtsystem_audit/i18n/es.po
odoo/addons/mgmtsystem_audit/i18n/es_CO.po
odoo/addons/mgmtsystem_audit/i18n/es_ES.po
odoo/addons/mgmtsystem_audit/i18n/fi.po
odoo/addons/mgmtsystem_audit/i18n/fr.po
odoo/addons/mgmtsystem_audit/i18n/gl.po
odoo/addons/mgmtsystem_audit/i18n/hr_HR.po
odoo/addons/mgmtsystem_audit/i18n/hu.po
odoo/addons/mgmtsystem_audit/i18n/it.po
odoo/addons/mgmtsystem_audit/i18n/lv.po
odoo/addons/mgmtsystem_audit/i18n/mgmtsystem_audit.pot
odoo/addons/mgmtsystem_audit/i18n/nb.po
odoo/addons/mgmtsystem_audit/i18n/nl.po
odoo/addons/mgmtsystem_audit/i18n/nl_NL.po
odoo/addons/mgmtsystem_audit/i18n/nn.po
odoo/addons/mgmtsystem_audit/i18n/pt.po
odoo/addons/mgmtsystem_audit/i18n/pt_BR.po
odoo/addons/mgmtsystem_audit/i18n/pt_PT.po
odoo/addons/mgmtsystem_audit/i18n/sl.po
odoo/addons/mgmtsystem_audit/i18n/sv.po
odoo/addons/mgmtsystem_audit/i18n/tr.po
odoo/addons/mgmtsystem_audit/i18n/vi.po
odoo/addons/mgmtsystem_audit/models/__init__.py
odoo/addons/mgmtsystem_audit/models/mgmtsystem_audit.py
odoo/addons/mgmtsystem_audit/models/mgmtsystem_nonconformity.py
odoo/addons/mgmtsystem_audit/models/mgmtsystem_verification_line.py
odoo/addons/mgmtsystem_audit/readme/CONFIGURE.md
odoo/addons/mgmtsystem_audit/readme/CONTRIBUTORS.md
odoo/addons/mgmtsystem_audit/readme/DESCRIPTION.md
odoo/addons/mgmtsystem_audit/readme/USAGE.md
odoo/addons/mgmtsystem_audit/report/audit.xml
odoo/addons/mgmtsystem_audit/report/mgmtsystem_audit_pivot.xml
odoo/addons/mgmtsystem_audit/report/report.xml
odoo_addon_mgmtsystem_audit-18.0.1.1.0.2.dist-info/METADATA
odoo_addon_mgmtsystem_audit-18.0.1.1.0.2.dist-info/WHEEL
odoo_addon_mgmtsystem_audit-18.0.1.1.0.2.dist-info/top_level.txt
odoo_addon_mgmtsystem_audit-18.0.1.1.0.2.dist-info/RECORD
